vasttrafik/__init__.py
vasttrafik/__main__.py
vasttrafik/journy_planner.py
vtjp-0.2.1.dist-info/LICENSE
vtjp-0.2.1.dist-info/METADATA
vtjp-0.2.1.dist-info/WHEEL
vtjp-0.2.1.dist-info/entry_points.txt
vtjp-0.2.1.dist-info/top_level.txt
vtjp-0.2.1.dist-info/zip-safe
vtjp-0.2.1.dist-info/RECORD
